pyGPGO/GPGO.py
pyGPGO/GPRegressor.py
pyGPGO/__init__.py
pyGPGO/acquisition.py
pyGPGO/covfunc.py
pyGPGO/logger.py
pyGPGO-0.1.0.dev1.dist-info/DESCRIPTION.rst
pyGPGO-0.1.0.dev1.dist-info/METADATA
pyGPGO-0.1.0.dev1.dist-info/RECORD
pyGPGO-0.1.0.dev1.dist-info/WHEEL
pyGPGO-0.1.0.dev1.dist-info/metadata.json
pyGPGO-0.1.0.dev1.dist-info/top_level.txt
