Metadata-Version: 2.0
Name: pyGPGO
Version: 0.1.0.dev1
Summary: Bayesian Optimization tools in Python
Home-page: https://github.com/hawk31/pyGPGO
Author: Jose Jimenez
Author-email: jose.jimenez@upf.edu
License: MIT
Keywords: machine-learning,optimization,bayesian
Platform: UNKNOWN
Classifier: Development Status :: 2 - Pre-Alpha
Classifier: License :: OSI Approved :: MIT License
Classifier: Programming Language :: Python :: 3.6
Classifier: Topic :: Scientific/Engineering :: Mathematics
Requires-Dist: cma
Requires-Dist: joblib
Requires-Dist: numpy
Requires-Dist: scipy
